daak/__init__.py
daak/_process.py
daak/_process_39.py
daak/process.py
daak/py.typed
daak-0.1.2.dist-info/METADATA
daak-0.1.2.dist-info/WHEEL
daak-0.1.2.dist-info/licenses/LICENSE
daak-0.1.2.dist-info/RECORD
