Metadata-Version: 2.4
Name: daak
Version: 0.1.2
Summary: Asynchronous subprocess runner
Author-email: Sean Toner <placeoftheway@gmail.com>
License-File: LICENSE
Requires-Python: >=3.9
